np_tools/__init__.py
np_tools/config.py
np_tools/file_io.py
np_tools/job_queues.py
np_tools/nwb.py
np_tools/openephys.py
np_tools/remote.py
np_tools-0.1.24.dist-info/METADATA
np_tools-0.1.24.dist-info/WHEEL
np_tools-0.1.24.dist-info/top_level.txt
np_tools-0.1.24.dist-info/RECORD
